pyRIF/__init__.py
pyRIF/pyRIF.py
pyRIF-1.0.4.dist-info/METADATA
pyRIF-1.0.4.dist-info/WHEEL
pyRIF-1.0.4.dist-info/top_level.txt
pyRIF-1.0.4.dist-info/RECORD
