Metadata-Version: 2.1
Name: pyRIF
Version: 1.0.4
Summary: Using Rotamer Interaction Fields from RIFGen/Dock in python
Home-page: https://github.com/psalveso/pyRIF
Author: Patrick Salveson
Author-email: patricksalveson@gmail.com
License: UNKNOWN
Platform: UNKNOWN
Classifier: Programming Language :: Python :: 3
Classifier: Topic :: Scientific/Engineering
Classifier: Topic :: Software Development
Classifier: License :: OSI Approved :: MIT License
Classifier: Operating System :: Unix
Requires-Dist: numpy
Requires-Dist: xbin
Requires-Dist: getpy
Requires-Dist: pynerf
Requires-Dist: h5py
